docs/PIEFACE_manual.pdf
docs/__init__.py
docs/api_reference.rst
docs/conf.py
docs/glossary.rst
docs/index.rst
docs/installation.rst
docs/introduction.rst
docs/license.rst
docs/recentchange.rst
docs/script_input.rst
docs/tutorial.rst
docs/images/PIEFACE.ico
docs/images/ellipsoid_icon_old.ico
docs/images/high_res_icon.png
docs/images/pieface_ellipsoidplot.png
docs/images/pieface_gui_labelled.png
pieface/CIFellipsoid.py
pieface/__init__.py
pieface/calcellipsoid.py
pieface/ellipsoid.py
pieface/multiCIF.py
pieface/pieface_gui.py
pieface/plotellipsoid.py
pieface/polyhedron.py
pieface/readcoords.py
pieface/writeproperties.py
pieface/data/PIEFACE.ico
pieface/data/__init__.py
pieface/data/high_res_icon.png
pieface/data/pieface.png
pieface/data/pieface.xbm
pieface/tests/__init__.py
pieface/tests/test_ellipsoid.py
pieface/tests/test_multiCIF.py
pieface/tests/test_polyhedron.py
pieface/tests/test_readcoords.py
pieface/tests/test_data/MnSnO3_COD1004021.cif
pieface/tests/test_data/__init__.py
pieface/tests/test_data/fayalite_COD1000064.cif
pieface-1.0.0.dist-info/DESCRIPTION.rst
pieface-1.0.0.dist-info/METADATA
pieface-1.0.0.dist-info/RECORD
pieface-1.0.0.dist-info/WHEEL
pieface-1.0.0.dist-info/entry_points.txt
pieface-1.0.0.dist-info/metadata.json
pieface-1.0.0.dist-info/top_level.txt
pieface_docs/PIEFACE_manual.pdf
pieface_docs/README.pdf
pieface_docs/__init__.py
pieface_docs/api_reference.rst
pieface_docs/conf.py
pieface_docs/glossary.rst
pieface_docs/index.rst
pieface_docs/installation.rst
pieface_docs/introduction.rst
pieface_docs/license.rst
pieface_docs/recentchange.rst
pieface_docs/script_input.rst
pieface_docs/tutorial.rst
pieface_docs/images/ellipsoid_icon_old.ico
pieface_docs/images/high_res_icon.png
pieface_docs/images/pieface.ico
pieface_docs/images/pieface_ellipsoidplot.png
pieface_docs/images/pieface_gui_labelled.png
test_data/MnSnO3_COD1004021.cif
test_data/__init__.py
test_data/__init__.pyc
test_data/fayalite_COD1000064.cif
tests/__init__.py
tests/test_ellipsoid.py
tests/test_multiCIF.py
tests/test_polyhedron.py
tests/test_readcoords.py
