Metadata-Version: 2.0
Name: pieface
Version: 1.0.0
Summary: A program for calculating minimum bounding ellipsoids forcrystallographic polyhedra and various related properties
Home-page: https://github.com/jcumby/PIEFACE
Author: James Cumby
Author-email: james.cumby@ed.ac.uk
License: MIT
Keywords: Polyhedra,Crystallography,Materials,Analysis,Distortion
Platform: UNKNOWN
Classifier: Development Status :: 3 - Alpha
Classifier: Natural Language :: English
Classifier: Topic :: Utilities
Classifier: License :: OSI Approved :: MIT License
Classifier: Programming Language :: Python :: 2
Classifier: Programming Language :: Python :: 2.6
Classifier: Programming Language :: Python :: 2.7
Requires-Dist: matplotlib (>=1.4.3)
Requires-Dist: multiprocessing (>=2.6.2.1)
Requires-Dist: numpy (>=1.9.2)
Requires-Dist: pandas (>=0.17.1)
Requires-Dist: pycifrw (>=3.3)
